{
	"id": "c004cb93-32ce-410b-8ce9-92c7300c2ef3",
	"name": "utn-phones",
	"values": [
		{
			"key": "Authorization",
			"value": "aa2bb900-0f7f-4be8-931b-ba7142afd693",
			"enabled": true
		},
		{
			"key": "backOfficeUrl",
			"value": "http://localhost:8080/backoffice",
			"enabled": true
		},
		{
			"key": "webUserUrl",
			"value": "http://localhost:8080/api",
			"enabled": true
		},
		{
			"key": "url",
			"value": "http://localhost:8080",
			"enabled": true
		},
		{
			"key": "idTariff",
			"value": "1",
			"enabled": true
		},
		{
			"key": "infrastructureUrl",
			"value": "http://localhost:8080/infrastructure",
			"enabled": true
		}
	],
	"_postman_variable_scope": "environment",
	"_postman_exported_at": "2020-07-02T00:54:59.169Z",
	"_postman_exported_using": "Postman/7.27.1"
}